_dazl/__init__.py
_dazl/__main__.py
_dazl/_logging.py
_dazl/codegen/__init__.py
_dazl/codegen/go.py
_dazl/codegen/go_header.py
_dazl/codegen/python.py
_dazl/codegen/python_grpc_pyi.py
_dazl/codegen/python_header.py
_dazl/codegen/python_init.py
_dazl/codegen/util.py
_dazl/collections.py
_dazl/generate_api.py
_dazl/protoc/__init__.py
_dazl/syntax/__init__.py
_dazl/syntax/python/__init__.py
_dazl/syntax/python/_basic.py
_dazl/syntax/python/imports.py
_dazl/syntax/python/pb.py
_dazl/syntax/python/symbols.py
_dazl/syntax/python/types.py
_dazl/update.py
dazl/__init__.py
dazl/__main__.py
dazl/_gen/__init__.py
dazl/_gen/com/__init__.py
dazl/_gen/com/daml/__init__.py
dazl/_gen/com/daml/daml_lf_1_17/__init__.py
dazl/_gen/com/daml/daml_lf_1_17/daml_lf_1_pb2.py
dazl/_gen/com/daml/daml_lf_1_17/daml_lf_1_pb2.pyi
dazl/_gen/com/daml/daml_lf_1_17/daml_lf_pb2.py
dazl/_gen/com/daml/daml_lf_1_17/daml_lf_pb2.pyi
dazl/_gen/com/daml/daml_lf_2_1/__init__.py
dazl/_gen/com/daml/daml_lf_2_1/daml_lf2_pb2.py
dazl/_gen/com/daml/daml_lf_2_1/daml_lf2_pb2.pyi
dazl/_gen/com/daml/daml_lf_2_1/daml_lf_pb2.py
dazl/_gen/com/daml/daml_lf_2_1/daml_lf_pb2.pyi
dazl/_gen/com/daml/ledger/__init__.py
dazl/_gen/com/daml/ledger/api/__init__.py
dazl/_gen/com/daml/ledger/api/v1/__init__.py
dazl/_gen/com/daml/ledger/api/v1/active_contracts_service_pb2.py
dazl/_gen/com/daml/ledger/api/v1/active_contracts_service_pb2.pyi
dazl/_gen/com/daml/ledger/api/v1/active_contracts_service_pb2_grpc.py
dazl/_gen/com/daml/ledger/api/v1/active_contracts_service_pb2_grpc.pyi
dazl/_gen/com/daml/ledger/api/v1/admin/__init__.py
dazl/_gen/com/daml/ledger/api/v1/admin/command_inspection_service_pb2.py
dazl/_gen/com/daml/ledger/api/v1/admin/command_inspection_service_pb2.pyi
dazl/_gen/com/daml/ledger/api/v1/admin/command_inspection_service_pb2_grpc.py
dazl/_gen/com/daml/ledger/api/v1/admin/command_inspection_service_pb2_grpc.pyi
dazl/_gen/com/daml/ledger/api/v1/admin/config_management_service_pb2.py
dazl-8.8.0.dist-info/LICENSE
dazl-8.8.0.dist-info/METADATA
dazl-8.8.0.dist-info/WHEEL
dazl-8.8.0.dist-info/entry_points.txt
dazl-8.8.0.dist-info/RECORD
