Metadata-Version: 2.3
Name: dazl
Version: 8.8.0
Summary: high-level Ledger API client for Daml ledgers
License: Apache-2.0
Keywords: daml,blockchain,dlt,distributed ledger,digital asset
Author: Davin K. Tanabe
Author-email: davin.tanabe@digitalasset.com
Requires-Python: >=3.10.0,<4.0.0
Classifier: License :: OSI Approved :: Apache Software License
Classifier: Programming Language :: Python :: 3
Classifier: Programming Language :: Python :: 3.10
Classifier: Programming Language :: Python :: 3.11
Classifier: Programming Language :: Python :: 3.12
Classifier: Programming Language :: Python :: 3.13
Provides-Extra: pygments
Provides-Extra: tls-testing
Requires-Dist: attrs (>=22.2.0)
Requires-Dist: googleapis_common_protos (>=1,<2)
Requires-Dist: grpcio (>=1.72.0,<2.0.0)
Requires-Dist: httpx (>=0.27.0,<0.28.0)
Requires-Dist: protobuf (>=6)
Requires-Dist: pyOpenSSL ; extra == "tls-testing"
Requires-Dist: pygments ; extra == "pygments"
Requires-Dist: python-dateutil (>=2.8.1)
Requires-Dist: semver
Requires-Dist: typing_extensions
Project-URL: Homepage, https://github.com/digital-asset/dazl-client
Project-URL: Repository, https://github.com/digital-asset/dazl-client
